MANIFEST.in
README
setup.py
FoneAstra.egg-info/PKG-INFO
FoneAstra.egg-info/SOURCES.txt
FoneAstra.egg-info/dependency_links.txt
FoneAstra.egg-info/requires.txt
FoneAstra.egg-info/top_level.txt
fa/__init__.py
fa/__init__.pyc
fa/apps.py
fa/models.py
fa/models.pyc
fa/urls.py
fa/utils.py
fa/views.py
fa/migrations/0001_initial.py
fa/migrations/0001_initial.pyc
fa/migrations/__init__.py
fa/migrations/__init__.pyc
fa/static/fa/flot/API.txt
fa/static/fa/flot/FAQ.txt
fa/static/fa/flot/LICENSE.txt
fa/static/fa/flot/Makefile
fa/static/fa/flot/NEWS.txt
fa/static/fa/flot/PLUGINS.txt
fa/static/fa/flot/README.txt
fa/static/fa/flot/excanvas.js
fa/static/fa/flot/excanvas.min.js
fa/static/fa/flot/jquery.colorhelpers.js
fa/static/fa/flot/jquery.colorhelpers.min.js
fa/static/fa/flot/jquery.flot.axislabels.js
fa/static/fa/flot/jquery.flot.crosshair.js
fa/static/fa/flot/jquery.flot.crosshair.min.js
fa/static/fa/flot/jquery.flot.fillbetween.js
fa/static/fa/flot/jquery.flot.fillbetween.min.js
fa/static/fa/flot/jquery.flot.image.js
fa/static/fa/flot/jquery.flot.image.min.js
fa/static/fa/flot/jquery.flot.js
fa/static/fa/flot/jquery.flot.min.js
fa/static/fa/flot/jquery.flot.navigate.js
fa/static/fa/flot/jquery.flot.navigate.min.js
fa/static/fa/flot/jquery.flot.pie.js
fa/static/fa/flot/jquery.flot.pie.min.js
fa/static/fa/flot/jquery.flot.resize.js
fa/static/fa/flot/jquery.flot.resize.min.js
fa/static/fa/flot/jquery.flot.selection.js
fa/static/fa/flot/jquery.flot.selection.min.js
fa/static/fa/flot/jquery.flot.stack.js
fa/static/fa/flot/jquery.flot.stack.min.js
fa/static/fa/flot/jquery.flot.symbol.js
fa/static/fa/flot/jquery.flot.symbol.min.js
fa/static/fa/flot/jquery.flot.threshold.js
fa/static/fa/flot/jquery.flot.threshold.min.js
fa/static/fa/flot/jquery.js
fa/static/fa/flot/jquery.min.js
fa/static/fa/flot/examples/ajax.html
fa/static/fa/flot/examples/annotating.html
fa/static/fa/flot/examples/arrow-down.gif
fa/static/fa/flot/examples/arrow-left.gif
fa/static/fa/flot/examples/arrow-right.gif
fa/static/fa/flot/examples/arrow-up.gif
fa/static/fa/flot/examples/basic.html
fa/static/fa/flot/examples/data-eu-gdp-growth-1.json
