Metadata-Version: 1.1
Name: FoneAstra
Version: 3.0.0
Summary: Django package necessary for running a FoneAstra server.
Home-page: https://bitbucket.org/pittsw/foneastra-base
Author: University of Washington CSE
Author-email: pittsw@uw.edu
License: BSD
Platform: UNKNOWN
Classifier: Development Status :: 4 - Beta
Classifier: Framework :: Django
Classifier: Intended Audience :: Healthcare Industry
